<?xml version="1.0"?>

<model-hints>
	<model name="com.liferay.frontend.view.state.model.FVSActiveEntry">
		<field name="mvccVersion" type="long" />
		<field name="uuid" type="String" />
		<field name="fvsActiveEntryId" type="long" />
		<field name="companyId" type="long" />
		<field name="userId" type="long" />
		<field name="userName" type="String" />
		<field name="createDate" type="Date" />
		<field name="modifiedDate" type="Date" />
		<field name="fvsEntryId" type="long" />
		<field name="clayDataSetDisplayId" type="String" />
		<field name="plid" type="long" />
		<field name="portletId" type="String">
			<hint name="max-length">200</hint>
		</field>
	</model>
	<model name="com.liferay.frontend.view.state.model.FVSEntry">
		<field name="mvccVersion" type="long" />
		<field name="uuid" type="String" />
		<field name="fvsEntryId" type="long" />
		<field name="companyId" type="long" />
		<field name="userId" type="long" />
		<field name="userName" type="String" />
		<field name="createDate" type="Date" />
		<field name="modifiedDate" type="Date" />
		<field name="viewState" type="String">
			<hint-collection name="CLOB" />
		</field>
	</model>
</model-hints>